Metadata-Version: 2.1
Name: silhouette2wireframe
Version: 0.0.2
Summary: Convert silhouette image to wireframe distorted by Perlin noise
Home-page: https://github.com/timpyrkov/silhouette2wireframe
Author: Tim Pyrkov
Author-email: tim.pyrkov@gmail.com
License: MIT License
Classifier: Programming Language :: Python :: 3
Classifier: License :: OSI Approved :: MIT License
Classifier: Topic :: Artistic Software
Requires-Python: >=3.6
License-File: LICENSE
